{
    "os": "Linux-5.4.0-121-generic-x86_64-with-glibc2.29",
    "python": "3.8.10",
    "heartbeatAt": "2023-04-28T17:32:14.515526",
    "startedAt": "2023-04-28T17:32:13.132371",
    "docker": null,
    "cuda": null,
    "args": [],
    "state": "running",
    "program": "main.py",
    "codePath": "src/_master_thesis_benge_supervised_learning/supervised_baseline/main.py",
    "git": {
        "remote": "https://github.com/nicikess/master-thesis-benge.git",
        "commit": "3f1269d845be81e16f415c45dd299d893cd1fa9a"
    },
    "email": "\u201cnicolaskesseli@gmail.com\u201d",
    "root": "/netscratch2/nkesseli/master-thesis-benge",
    "host": "cd2b6d326f88",
    "username": "3023",
    "executable": "/usr/bin/python",
    "cpu_count": 48,
    "cpu_count_logical": 96,
    "cpu_freq": {
        "current": 3285.448,
        "min": 1200.0,
        "max": 3700.0
    },
    "cpu_freq_per_core": [
        {
            "current": 3399.994,
            "min": 1200.0,
            "max": 3700.0
        },
        {
            "current": 3231.715,
            "min": 1200.0,
            "max": 3700.0
        },
        {
            "current": 3231.066,
            "min": 1200.0,
            "max": 3700.0
        },
        {
            "current": 2900.402,
            "min": 1200.0,
            "max": 3700.0
        },
        {
            "current": 3390.124,
            "min": 1200.0,
            "max": 3700.0
        },
        {
            "current": 3039.366,
            "min": 1200.0,
            "max": 3700.0
        },
        {
            "current": 3018.308,
            "min": 1200.0,
            "max": 3700.0
        },
        {
            "current": 3114.403,
            "min": 1200.0,
            "max": 3700.0
        },
        {
            "current": 2938.255,
            "min": 1200.0,
            "max": 3700.0
        },
        {
            "current": 3405.761,
            "min": 1200.0,
            "max": 3700.0
        },
        {
            "current": 3400.026,
            "min": 1200.0,
            "max": 3700.0
        },
        {
            "current": 3283.022,
            "min": 1200.0,
            "max": 3700.0
        },
        {
            "current": 3400.0,
            "min": 1200.0,
            "max": 3700.0
        },
        {
            "current": 3399.997,
            "min": 1200.0,
            "max": 3700.0
        },
        {
            "current": 3331.974,
            "min": 1200.0,
            "max": 3700.0
        },
        {
            "current": 3399.999,
            "min": 1200.0,
            "max": 3700.0
        },
        {
            "current": 3189.418,
            "min": 1200.0,
            "max": 3700.0
        },
        {
            "current": 3389.896,
            "min": 1200.0,
            "max": 3700.0
        },
        {
            "current": 3400.0,
            "min": 1200.0,
            "max": 3700.0
        },
        {
            "current": 3399.972,
            "min": 1200.0,
            "max": 3700.0
        },
        {
            "current": 3194.96,
            "min": 1200.0,
            "max": 3700.0
        },
        {
            "current": 3399.78,
            "min": 1200.0,
            "max": 3700.0
        },
        {
            "current": 2904.786,
            "min": 1200.0,
            "max": 3700.0
        },
        {
            "current": 3122.214,
            "min": 1200.0,
            "max": 3700.0
        },
        {
            "current": 3399.674,
            "min": 1200.0,
            "max": 3700.0
        },
        {
            "current": 3399.999,
            "min": 1200.0,
            "max": 3700.0
        },
        {
            "current": 3341.867,
            "min": 1200.0,
            "max": 3700.0
        },
        {
            "current": 3346.294,
            "min": 1200.0,
            "max": 3700.0
        },
        {
            "current": 3074.473,
            "min": 1200.0,
            "max": 3700.0
        },
        {
            "current": 3367.999,
            "min": 1200.0,
            "max": 3700.0
        },
        {
            "current": 2879.217,
            "min": 1200.0,
            "max": 3700.0
        },
        {
            "current": 3195.382,
            "min": 1200.0,
            "max": 3700.0
        },
        {
            "current": 3171.791,
            "min": 1200.0,
            "max": 3700.0
        },
        {
            "current": 3398.578,
            "min": 1200.0,
            "max": 3700.0
        },
        {
            "current": 3344.17,
            "min": 1200.0,
            "max": 3700.0
        },
        {
            "current": 3400.04,
            "min": 1200.0,
            "max": 3700.0
        },
        {
            "current": 3399.772,
            "min": 1200.0,
            "max": 3700.0
        },
        {
            "current": 3397.448,
            "min": 1200.0,
            "max": 3700.0
        },
        {
            "current": 3400.0,
            "min": 1200.0,
            "max": 3700.0
        },
        {
            "current": 3386.934,
            "min": 1200.0,
            "max": 3700.0
        },
        {
            "current": 3292.021,
            "min": 1200.0,
            "max": 3700.0
        },
        {
            "current": 3224.398,
            "min": 1200.0,
            "max": 3700.0
        },
        {
            "current": 3399.999,
            "min": 1200.0,
            "max": 3700.0
        },
        {
            "current": 3399.991,
            "min": 1200.0,
            "max": 3700.0
        },
        {
            "current": 3397.39,
            "min": 1200.0,
            "max": 3700.0
        },
        {
            "current": 3216.313,
            "min": 1200.0,
            "max": 3700.0
        },
        {
            "current": 3292.825,
            "min": 1200.0,
            "max": 3700.0
        },
        {
            "current": 3398.553,
            "min": 1200.0,
            "max": 3700.0
        },
        {
            "current": 3399.999,
            "min": 1200.0,
            "max": 3700.0
        },
        {
            "current": 2903.415,
            "min": 1200.0,
            "max": 3700.0
        },
        {
            "current": 2914.708,
            "min": 1200.0,
            "max": 3700.0
        },
        {
            "current": 3018.186,
            "min": 1200.0,
            "max": 3700.0
        },
        {
            "current": 3358.915,
            "min": 1200.0,
            "max": 3700.0
        },
        {
            "current": 3106.734,
            "min": 1200.0,
            "max": 3700.0
        },
        {
            "current": 3083.858,
            "min": 1200.0,
            "max": 3700.0
        },
        {
            "current": 3154.32,
            "min": 1200.0,
            "max": 3700.0
        },
        {
            "current": 2785.212,
            "min": 1200.0,
            "max": 3700.0
        },
        {
            "current": 3399.999,
            "min": 1200.0,
            "max": 3700.0
        },
        {
            "current": 3399.999,
            "min": 1200.0,
            "max": 3700.0
        },
        {
            "current": 3000.256,
            "min": 1200.0,
            "max": 3700.0
        },
        {
            "current": 3399.883,
            "min": 1200.0,
            "max": 3700.0
        },
        {
            "current": 3399.997,
            "min": 1200.0,
            "max": 3700.0
        },
        {
            "current": 2997.782,
            "min": 1200.0,
            "max": 3700.0
        },
        {
            "current": 3399.983,
            "min": 1200.0,
            "max": 3700.0
        },
        {
            "current": 3233.251,
            "min": 1200.0,
            "max": 3700.0
        },
        {
            "current": 3386.242,
            "min": 1200.0,
            "max": 3700.0
        },
        {
            "current": 3398.885,
            "min": 1200.0,
            "max": 3700.0
        },
        {
            "current": 3399.999,
            "min": 1200.0,
            "max": 3700.0
        },
        {
            "current": 3253.515,
            "min": 1200.0,
            "max": 3700.0
        },
        {
            "current": 2990.579,
            "min": 1200.0,
            "max": 3700.0
        },
        {
            "current": 2993.95,
            "min": 1200.0,
            "max": 3700.0
        },
        {
            "current": 2991.972,
            "min": 1200.0,
            "max": 3700.0
        },
        {
            "current": 3399.197,
            "min": 1200.0,
            "max": 3700.0
        },
        {
            "current": 3399.991,
            "min": 1200.0,
            "max": 3700.0
        },
        {
            "current": 3321.779,
            "min": 1200.0,
            "max": 3700.0
        },
        {
            "current": 3398.61,
            "min": 1200.0,
            "max": 3700.0
        },
        {
            "current": 3014.905,
            "min": 1200.0,
            "max": 3700.0
        },
        {
            "current": 3397.676,
            "min": 1200.0,
            "max": 3700.0
        },
        {
            "current": 3377.774,
            "min": 1200.0,
            "max": 3700.0
        },
        {
            "current": 3069.789,
            "min": 1200.0,
            "max": 3700.0
        },
        {
            "current": 3399.589,
            "min": 1200.0,
            "max": 3700.0
        },
        {
            "current": 3023.441,
            "min": 1200.0,
            "max": 3700.0
        },
        {
            "current": 3259.832,
            "min": 1200.0,
            "max": 3700.0
        },
        {
            "current": 3400.014,
            "min": 1200.0,
            "max": 3700.0
        },
        {
            "current": 3399.803,
            "min": 1200.0,
            "max": 3700.0
        },
        {
            "current": 3139.68,
            "min": 1200.0,
            "max": 3700.0
        },
        {
            "current": 3400.446,
            "min": 1200.0,
            "max": 3700.0
        },
        {
            "current": 3398.126,
            "min": 1200.0,
            "max": 3700.0
        },
        {
            "current": 3370.358,
            "min": 1200.0,
            "max": 3700.0
        },
        {
            "current": 3299.274,
            "min": 1200.0,
            "max": 3700.0
        },
        {
            "current": 3324.582,
            "min": 1200.0,
            "max": 3700.0
        },
        {
            "current": 3399.899,
            "min": 1200.0,
            "max": 3700.0
        },
        {
            "current": 3399.928,
            "min": 1200.0,
            "max": 3700.0
        },
        {
            "current": 3397.397,
            "min": 1200.0,
            "max": 3700.0
        },
        {
            "current": 3112.565,
            "min": 1200.0,
            "max": 3700.0
        },
        {
            "current": 3399.448,
            "min": 1200.0,
            "max": 3700.0
        }
    ],
    "disk": {
        "total": 878.5721054077148,
        "used": 470.10036849975586
    },
    "gpu": "Tesla V100-SXM3-32GB",
    "gpu_count": 1,
    "gpu_devices": [
        {
            "name": "Tesla V100-SXM3-32GB",
            "memory_total": 34089730048
        }
    ],
    "memory": {
        "total": 1510.565860748291
    }
}
