{
    "os": "Linux-5.4.0-121-generic-x86_64-with-glibc2.29",
    "python": "3.8.10",
    "heartbeatAt": "2023-04-17T07:49:40.230964",
    "startedAt": "2023-04-17T07:49:38.877890",
    "docker": null,
    "cuda": null,
    "args": [],
    "state": "running",
    "program": "main.py",
    "codePath": "src/_master_thesis_benge_supervised_learning/classification_baseline/main.py",
    "git": {
        "remote": "https://github.com/nicikess/master-thesis-benge.git",
        "commit": "1c08607be9246583a4fc0b0f3faa548841cc55cd"
    },
    "email": "\u201cnicolaskesseli@gmail.com\u201d",
    "root": "/netscratch2/nkesseli/master-thesis-benge",
    "host": "54ae5b2345c3",
    "username": "3023",
    "executable": "/usr/bin/python",
    "cpu_count": 48,
    "cpu_count_logical": 96,
    "cpu_freq": {
        "current": 3176.3417499999996,
        "min": 1200.0,
        "max": 3700.0
    },
    "cpu_freq_per_core": [
        {
            "current": 3285.988,
            "min": 1200.0,
            "max": 3700.0
        },
        {
            "current": 2933.386,
            "min": 1200.0,
            "max": 3700.0
        },
        {
            "current": 2954.079,
            "min": 1200.0,
            "max": 3700.0
        },
        {
            "current": 3197.215,
            "min": 1200.0,
            "max": 3700.0
        },
        {
            "current": 3051.458,
            "min": 1200.0,
            "max": 3700.0
        },
        {
            "current": 3209.113,
            "min": 1200.0,
            "max": 3700.0
        },
        {
            "current": 3152.423,
            "min": 1200.0,
            "max": 3700.0
        },
        {
            "current": 3090.117,
            "min": 1200.0,
            "max": 3700.0
        },
        {
            "current": 3181.099,
            "min": 1200.0,
            "max": 3700.0
        },
        {
            "current": 3136.273,
            "min": 1200.0,
            "max": 3700.0
        },
        {
            "current": 2903.242,
            "min": 1200.0,
            "max": 3700.0
        },
        {
            "current": 3376.724,
            "min": 1200.0,
            "max": 3700.0
        },
        {
            "current": 2948.589,
            "min": 1200.0,
            "max": 3700.0
        },
        {
            "current": 3323.615,
            "min": 1200.0,
            "max": 3700.0
        },
        {
            "current": 2923.627,
            "min": 1200.0,
            "max": 3700.0
        },
        {
            "current": 2884.641,
            "min": 1200.0,
            "max": 3700.0
        },
        {
            "current": 3116.923,
            "min": 1200.0,
            "max": 3700.0
        },
        {
            "current": 3400.0,
            "min": 1200.0,
            "max": 3700.0
        },
        {
            "current": 2863.138,
            "min": 1200.0,
            "max": 3700.0
        },
        {
            "current": 3340.342,
            "min": 1200.0,
            "max": 3700.0
        },
        {
            "current": 2884.625,
            "min": 1200.0,
            "max": 3700.0
        },
        {
            "current": 3401.263,
            "min": 1200.0,
            "max": 3700.0
        },
        {
            "current": 3318.661,
            "min": 1200.0,
            "max": 3700.0
        },
        {
            "current": 3404.032,
            "min": 1200.0,
            "max": 3700.0
        },
        {
            "current": 3369.319,
            "min": 1200.0,
            "max": 3700.0
        },
        {
            "current": 3394.53,
            "min": 1200.0,
            "max": 3700.0
        },
        {
            "current": 3402.637,
            "min": 1200.0,
            "max": 3700.0
        },
        {
            "current": 3350.265,
            "min": 1200.0,
            "max": 3700.0
        },
        {
            "current": 3347.03,
            "min": 1200.0,
            "max": 3700.0
        },
        {
            "current": 2882.595,
            "min": 1200.0,
            "max": 3700.0
        },
        {
            "current": 3077.738,
            "min": 1200.0,
            "max": 3700.0
        },
        {
            "current": 3025.913,
            "min": 1200.0,
            "max": 3700.0
        },
        {
            "current": 3240.418,
            "min": 1200.0,
            "max": 3700.0
        },
        {
            "current": 3116.552,
            "min": 1200.0,
            "max": 3700.0
        },
        {
            "current": 3088.065,
            "min": 1200.0,
            "max": 3700.0
        },
        {
            "current": 2924.004,
            "min": 1200.0,
            "max": 3700.0
        },
        {
            "current": 2877.72,
            "min": 1200.0,
            "max": 3700.0
        },
        {
            "current": 2807.613,
            "min": 1200.0,
            "max": 3700.0
        },
        {
            "current": 3228.583,
            "min": 1200.0,
            "max": 3700.0
        },
        {
            "current": 3152.332,
            "min": 1200.0,
            "max": 3700.0
        },
        {
            "current": 2941.719,
            "min": 1200.0,
            "max": 3700.0
        },
        {
            "current": 2905.893,
            "min": 1200.0,
            "max": 3700.0
        },
        {
            "current": 2887.425,
            "min": 1200.0,
            "max": 3700.0
        },
        {
            "current": 3002.286,
            "min": 1200.0,
            "max": 3700.0
        },
        {
            "current": 3399.817,
            "min": 1200.0,
            "max": 3700.0
        },
        {
            "current": 3238.063,
            "min": 1200.0,
            "max": 3700.0
        },
        {
            "current": 3385.248,
            "min": 1200.0,
            "max": 3700.0
        },
        {
            "current": 2822.501,
            "min": 1200.0,
            "max": 3700.0
        },
        {
            "current": 3000.71,
            "min": 1200.0,
            "max": 3700.0
        },
        {
            "current": 3001.525,
            "min": 1200.0,
            "max": 3700.0
        },
        {
            "current": 3038.127,
            "min": 1200.0,
            "max": 3700.0
        },
        {
            "current": 3219.627,
            "min": 1200.0,
            "max": 3700.0
        },
        {
            "current": 3043.356,
            "min": 1200.0,
            "max": 3700.0
        },
        {
            "current": 2972.661,
            "min": 1200.0,
            "max": 3700.0
        },
        {
            "current": 3334.771,
            "min": 1200.0,
            "max": 3700.0
        },
        {
            "current": 3041.823,
            "min": 1200.0,
            "max": 3700.0
        },
        {
            "current": 3148.78,
            "min": 1200.0,
            "max": 3700.0
        },
        {
            "current": 2948.596,
            "min": 1200.0,
            "max": 3700.0
        },
        {
            "current": 2884.191,
            "min": 1200.0,
            "max": 3700.0
        },
        {
            "current": 3362.154,
            "min": 1200.0,
            "max": 3700.0
        },
        {
            "current": 3317.009,
            "min": 1200.0,
            "max": 3700.0
        },
        {
            "current": 2987.269,
            "min": 1200.0,
            "max": 3700.0
        },
        {
            "current": 3169.249,
            "min": 1200.0,
            "max": 3700.0
        },
        {
            "current": 2885.137,
            "min": 1200.0,
            "max": 3700.0
        },
        {
            "current": 3396.272,
            "min": 1200.0,
            "max": 3700.0
        },
        {
            "current": 3405.241,
            "min": 1200.0,
            "max": 3700.0
        },
        {
            "current": 2943.203,
            "min": 1200.0,
            "max": 3700.0
        },
        {
            "current": 3397.084,
            "min": 1200.0,
            "max": 3700.0
        },
        {
            "current": 2880.792,
            "min": 1200.0,
            "max": 3700.0
        },
        {
            "current": 3399.999,
            "min": 1200.0,
            "max": 3700.0
        },
        {
            "current": 3319.544,
            "min": 1200.0,
            "max": 3700.0
        },
        {
            "current": 3236.039,
            "min": 1200.0,
            "max": 3700.0
        },
        {
            "current": 3400.095,
            "min": 1200.0,
            "max": 3700.0
        },
        {
            "current": 3394.987,
            "min": 1200.0,
            "max": 3700.0
        },
        {
            "current": 3400.0,
            "min": 1200.0,
            "max": 3700.0
        },
        {
            "current": 3349.545,
            "min": 1200.0,
            "max": 3700.0
        },
        {
            "current": 3305.417,
            "min": 1200.0,
            "max": 3700.0
        },
        {
            "current": 2884.616,
            "min": 1200.0,
            "max": 3700.0
        },
        {
            "current": 2920.788,
            "min": 1200.0,
            "max": 3700.0
        },
        {
            "current": 3040.347,
            "min": 1200.0,
            "max": 3700.0
        },
        {
            "current": 3238.249,
            "min": 1200.0,
            "max": 3700.0
        },
        {
            "current": 3362.009,
            "min": 1200.0,
            "max": 3700.0
        },
        {
            "current": 3311.885,
            "min": 1200.0,
            "max": 3700.0
        },
        {
            "current": 3289.401,
            "min": 1200.0,
            "max": 3700.0
        },
        {
            "current": 3155.991,
            "min": 1200.0,
            "max": 3700.0
        },
        {
            "current": 3135.623,
            "min": 1200.0,
            "max": 3700.0
        },
        {
            "current": 3189.455,
            "min": 1200.0,
            "max": 3700.0
        },
        {
            "current": 3354.792,
            "min": 1200.0,
            "max": 3700.0
        },
        {
            "current": 3392.029,
            "min": 1200.0,
            "max": 3700.0
        },
        {
            "current": 2885.098,
            "min": 1200.0,
            "max": 3700.0
        },
        {
            "current": 2881.339,
            "min": 1200.0,
            "max": 3700.0
        },
        {
            "current": 3237.209,
            "min": 1200.0,
            "max": 3700.0
        },
        {
            "current": 3389.181,
            "min": 1200.0,
            "max": 3700.0
        },
        {
            "current": 3262.455,
            "min": 1200.0,
            "max": 3700.0
        },
        {
            "current": 3036.243,
            "min": 1200.0,
            "max": 3700.0
        },
        {
            "current": 3324.564,
            "min": 1200.0,
            "max": 3700.0
        }
    ],
    "disk": {
        "total": 878.5721054077148,
        "used": 494.1064987182617
    },
    "gpu": "Tesla V100-SXM3-32GB",
    "gpu_count": 1,
    "gpu_devices": [
        {
            "name": "Tesla V100-SXM3-32GB",
            "memory_total": 34089730048
        }
    ],
    "memory": {
        "total": 1510.5658645629883
    }
}
